config/__init__.py
config/asgi.py
config/settings.py
config/urls.py
config/wsgi.py
django_base_integration/__init__.py
django_base_integration/admin.py
django_base_integration/apps.py
django_base_integration/managers.py
django_base_integration/models.py
django_base_integration/permissions.py
django_base_integration/serializers.py
django_base_integration/signals.py
django_base_integration/urls.py
django_base_integration/views.py
django_base_integration/docker/Dockerfile
django_base_integration/docker/docker-compose.yml
django_base_integration/static/drf-yasg/README
django_base_integration/static/drf-yasg/immutable.js
django_base_integration/static/drf-yasg/immutable.min.js
django_base_integration/static/drf-yasg/insQ.js
django_base_integration/static/drf-yasg/insQ.min.js
django_base_integration/static/drf-yasg/redoc-init.js
django_base_integration/static/drf-yasg/style.css
django_base_integration/static/drf-yasg/swagger-ui-init.js
django_base_integration/static/drf-yasg/swagger-ui-dist/LICENSE
django_base_integration/static/drf-yasg/swagger-ui-dist/NOTICE
django_base_integration/static/drf-yasg/swagger-ui-dist/absolute-path.js
django_base_integration/static/drf-yasg/swagger-ui-dist/favicon-32x32.png
django_base_integration/static/drf-yasg/swagger-ui-dist/index.css
django_base_integration/static/drf-yasg/swagger-ui-dist/index.js
django_base_integration/static/drf-yasg/swagger-ui-dist/oauth2-redirect.html
django_base_integration/static/drf-yasg/swagger-ui-dist/swagger-initializer.js
django_base_integration/static/drf-yasg/swagger-ui-dist/swagger-ui-bundle.js
django_base_integration/static/drf-yasg/swagger-ui-dist/swagger-ui-bundle.js.map
django_base_integration/static/drf-yasg/swagger-ui-dist/swagger-ui-es-bundle-core.js
django_base_integration/static/drf-yasg/swagger-ui-dist/swagger-ui-es-bundle-core.js.map
django_base_integration/static/drf-yasg/swagger-ui-dist/swagger-ui-es-bundle.js
django_base_integration-0.2.dist-info/LICENSE
django_base_integration-0.2.dist-info/METADATA
django_base_integration-0.2.dist-info/WHEEL
django_base_integration-0.2.dist-info/top_level.txt
django_base_integration-0.2.dist-info/RECORD
