Metadata-Version: 2.1
Name: django-base-integration
Version: 0.2
Summary: A Django app integrator
Author-email: Bogdan Belenesku <bogdanbelenesku@gmail.com>
Classifier: Environment :: Web Environment
Classifier: Framework :: Django
Classifier: Framework :: Django :: 4.2
Classifier: Intended Audience :: Developers
Classifier: License :: OSI Approved :: BSD License
Classifier: Operating System :: OS Independent
Classifier: Programming Language :: Python
Classifier: Programming Language :: Python :: 3
Classifier: Programming Language :: Python :: 3 :: Only
Classifier: Programming Language :: Python :: 3.11
Classifier: Programming Language :: Python :: 3.12
Classifier: Topic :: Internet :: WWW/HTTP
Classifier: Topic :: Internet :: WWW/HTTP :: Dynamic Content
Requires-Python: >=3.11
License-File: LICENSE
Requires-Dist: django >=4.2
Requires-Dist: coreapi ==2.3.3
Requires-Dist: coreschema ==0.0.4
Requires-Dist: django-coreapi ==2.3.0
Requires-Dist: django-debug-toolbar ==4.1.0
Requires-Dist: djangorestframework ==3.14.0
Requires-Dist: djangorestframework-simplejwt ==5.2.2
Requires-Dist: drf-yasg ==1.21.7
Requires-Dist: psycopg2-binary ==2.9.6
Requires-Dist: PyJWT ==2.8.0
Requires-Dist: python-dotenv ===1.0.0
